kegg_ingest/__init__.py
kegg_ingest/cli.py
kegg_ingest/main.py
kegg_ingest/utils.py
kegg_ingest-0.0.1.dist-info/LICENSE
kegg_ingest-0.0.1.dist-info/METADATA
kegg_ingest-0.0.1.dist-info/WHEEL
kegg_ingest-0.0.1.dist-info/entry_points.txt
kegg_ingest-0.0.1.dist-info/RECORD
