Metadata-Version: 2.1
Name: kegg-ingest
Version: 0.0.1
Summary: kegg-ingest
License: MIT
Author: Harshad Hegde
Author-email: hhegde@lbl.gov
Requires-Python: >=3.9,<4.0
Classifier: License :: OSI Approved :: MIT License
Classifier: Programming Language :: Python :: 3
Classifier: Programming Language :: Python :: 3.9
Classifier: Programming Language :: Python :: 3.10
Classifier: Programming Language :: Python :: 3.11
Classifier: Programming Language :: Python :: 3.12
Requires-Dist: bioservices (>=1.11.2,<2.0.0)
Requires-Dist: click
Requires-Dist: duckdb (>=1.0.0,<2.0.0)
Requires-Dist: importlib-metadata (>=8.2.0)
Requires-Dist: pandas (>=2.2.2,<3.0.0)
Requires-Dist: requests-cache (>=1.2.1,<2.0.0)
